modgraph/__init__.py
modgraph/__main__.py
modgraph/main.py
modgraph/modgraph.py
modgraph-0.2.2.dist-info/LICENSE
modgraph-0.2.2.dist-info/METADATA
modgraph-0.2.2.dist-info/WHEEL
modgraph-0.2.2.dist-info/top_level.txt
modgraph-0.2.2.dist-info/RECORD
