Metadata-Version: 2.1
Name: modgraph
Version: 0.2.2
Summary: a tool to analyze sample overlap between tracker module files
Author-email: Ilia Pozdnyakov <ilia.pozdnyakov@ya.ru>
License: MIT
Keywords: tracker,music,samples
Classifier: Development Status :: 3 - Alpha
Classifier: Environment :: Console
Classifier: Topic :: Multimedia :: Sound/Audio :: Analysis
Classifier: Topic :: Utilities
Classifier: License :: OSI Approved :: MIT License
Requires-Python: >=3.10
License-File: LICENSE
Requires-Dist: trackrip (>=2.0.0)
